Lucifer_STT/_init_.py
lucifer_stt-0.1.dist-info/METADATA
lucifer_stt-0.1.dist-info/WHEEL
lucifer_stt-0.1.dist-info/top_level.txt
lucifer_stt-0.1.dist-info/RECORD
