Metadata-Version: 2.4
Name: Lucifer-STT
Version: 0.1
Summary: this is speech to text package created by Shreyas Warik
Author: Shreyas Warik
Author-email: lucifer140705@gmail.com
Dynamic: author
Dynamic: author-email
Dynamic: summary
